.DS_Store
lvr/.data.py.swp
lvr/__init__.py
lvr/data.py
lvr/helpers.py
lvr/data/bells.csv
lvr/data/boxoffice.csv
lvr/data/debris_masses.csv
lvr/data/exoplanets.json
lvr/data/flight_delays.csv
lvr/data/forest_fires.csv
lvr/data/french_rail_passengers.csv
lvr/data/german_highways.csv
lvr/data/german_motorways.csv
lvr/data/hopei_rain.csv
lvr/data/hopei_sun.csv
lvr/data/indian_trains_passing.csv
lvr/data/jre_rail_passengers.csv
lvr/data/lakes_level_1.json
lvr/data/lakes_surface.csv
lvr/data/meteorites.csv
lvr/data/missing_teeth.csv
lvr/data/stars.json
lvr/data/stars_masses.csv
lvr/data/stars_surfaces.csv
lvr/data/sunspots.csv
lvr/data/swiss_public_transport_delays.csv
lvr/data/swiss_rail_passengers.csv
lvr/data/titanic_fares.csv
lvr/data/tree_vol.csv
lvr/data/us_bridges.csv
lvr/data/us_power_plants.csv
lvr/data/wkzs.csv
lvr/data/women_intercourse.csv
lvr-0.1.2.dist-info/METADATA
lvr-0.1.2.dist-info/WHEEL
lvr-0.1.2.dist-info/top_level.txt
lvr-0.1.2.dist-info/RECORD
