Metadata-Version: 2.1
Name: lvr
Version: 0.1.2
Summary: UNKNOWN
Home-page: https://hg.sr.ht/~bwe/lvr
Author: Benjamin Weber
Author-email: mail@bwe.im
License: UNKNOWN
Platform: UNKNOWN
Classifier: Development Status :: 4 - Beta
Classifier: Programming Language :: Python :: 3
Classifier: Programming Language :: Python :: 3.4
Classifier: Programming Language :: Python :: 3.5
Classifier: Programming Language :: Python :: 3.6
Requires-Dist: numpy
Requires-Dist: tabulate
Provides-Extra: test
Requires-Dist: pytest ; extra == 'test'
